slpp.py
SLPP_23-1.1.dist-info/DESCRIPTION.rst
SLPP_23-1.1.dist-info/METADATA
SLPP_23-1.1.dist-info/RECORD
SLPP_23-1.1.dist-info/WHEEL
SLPP_23-1.1.dist-info/metadata.json
SLPP_23-1.1.dist-info/top_level.txt
