Metadata-Version: 1.0
Name: SLPP-23
Version: 1.1
Summary: SLPP-23 is a simple lua-python data structures parser
Home-page: https://github.com/IlyaSkriblovsky/slpp-23
Author: Ilya Skriblovsky
Author-email: ilyaskriblovsky@gmail.com
License: https://github.com/IlyaSkriblovsky/slpp-23/blob/master/LICENSE
Keywords: lua
Platform: UNKNOWN
